{
  "test": "Order API - 1000 VUs Stress Test",
  "timestamp": "2025-12-12T20:37:15.531Z",
  "testDuration": "1262.06s",
  "metrics": {
    "total_requests": 38591,
    "failed_requests": 1625,
    "failed_rate": "4.21%",
    "avg_response_time": "3606.02",
    "min_response_time": "3.22",
    "med_response_time": "1191.89",
    "max_response_time": "60146.12",
    "p90_response_time": "5948.27",
    "p95_response_time": "7726.11",
    "p99_response_time": "60000.67",
    "avg_waiting_time": "3605.20",
    "p95_waiting_time": "7721.82",
    "avg_blocked_time": "0.14",
    "avg_connecting_time": "0.11",
    "data_sent": "16.68 MB",
    "data_received": "223.88 MB",
    "requests_per_second": "30.58",
    "orders_created": 3758,
    "orders_read": 17718,
    "items_added": 554,
    "error_count": 242,
    "success_rate": "93.67%",
    "max_vus": 300,
    "iterations_completed": 19883,
    "avg_iteration_duration": "9515.72"
  },
  "k8sRecommendation": {
    "serviceName": "order-svc",
    "replicas": 3,
    "resources": {
      "requests": {
        "cpu": "1000m",
        "memory": "768Mi"
      },
      "limits": {
        "cpu": "4000m",
        "memory": "1536Mi"
      }
    },
    "metrics": {
      "maxVUs": 300,
      "avgResponseTime": "3606.02",
      "p95ResponseTime": "7726.11",
      "p99ResponseTime": "60000.67",
      "errorRate": "4.21",
      "throughput": "30.58"
    }
  },
  "rawData": {
    "options": {
      "summaryTrendStats": [
        "avg",
        "min",
        "med",
        "max",
        "p(90)",
        "p(95)",
        "p(99)"
      ],
      "summaryTimeUnit": "",
      "noColor": false
    },
    "state": {
      "testRunDurationMs": 1262056.9322,
      "isStdOutTTY": true,
      "isStdErrTTY": true
    },
    "metrics": {
      "orders_created": {
        "type": "counter",
        "contains": "default",
        "values": {
          "rate": 2.9776786641860182,
          "count": 3758
        }
      },
      "data_received": {
        "contains": "data",
        "values": {
          "count": 234759404,
          "rate": 186013.32317930437
        },
        "type": "counter"
      },
      "http_reqs": {
        "contains": "default",
        "values": {
          "count": 38591,
          "rate": 30.577859853539817
        },
        "type": "counter"
      },
      "orders_read": {
        "type": "counter",
        "contains": "default",
        "values": {
          "count": 17718,
          "rate": 14.038986315073942
        }
      },
      "order_create_latency": {
        "contains": "default",
        "values": {
          "p(90)": 7502.4,
          "p(95)": 36909.049999997966,
          "p(99)": 60015.01,
          "avg": 6100.78025,
          "min": 117,
          "med": 2873,
          "max": 60289
        },
        "thresholds": {
          "p(95)<30000": {
            "ok": false
          }
        },
        "type": "trend"
      },
      "order_read_latency": {
        "type": "trend",
        "contains": "default",
        "values": {
          "avg": 1308.4920491710839,
          "min": 4,
          "med": 853,
          "max": 12990,
          "p(90)": 2920,
          "p(95)": 3227,
          "p(99)": 5692
        },
        "thresholds": {
          "p(95)<15000": {
            "ok": true
          }
        }
      },
      "http_req_blocked": {
        "type": "trend",
        "contains": "time",
        "values": {
          "med": 0,
          "max": 205.5734,
          "p(90)": 0,
          "p(95)": 0.5924499999999999,
          "p(99)": 2.8427099999999967,
          "avg": 0.13963092430877708,
          "min": 0
        }
      },
      "http_req_receiving": {
        "type": "trend",
        "contains": "time",
        "values": {
          "max": 324.8985,
          "p(90)": 1.0111,
          "p(95)": 1.4116,
          "p(99)": 4.066549999999997,
          "avg": 0.6611427690394148,
          "min": 0,
          "med": 0
        }
      },
      "iterations": {
        "type": "counter",
        "contains": "default",
        "values": {
          "count": 19883,
          "rate": 15.754439829699468
        }
      },
      "http_req_sending": {
        "type": "trend",
        "contains": "time",
        "values": {
          "med": 0,
          "max": 251.3809,
          "p(90)": 0,
          "p(95)": 0.58405,
          "p(99)": 1.5309099999999998,
          "avg": 0.15374426420668091,
          "min": 0
        }
      },
      "vus": {
        "type": "gauge",
        "contains": "default",
        "values": {
          "value": 4,
          "min": 0,
          "max": 300
        }
      },
      "items_added": {
        "type": "counter",
        "contains": "default",
        "values": {
          "count": 554,
          "rate": 0.43896593399655515
        }
      },
      "http_req_duration": {
        "values": {
          "avg": 3606.0156879168444,
          "min": 3.223,
          "med": 1191.8916,
          "max": 60146.1234,
          "p(90)": 5948.2676,
          "p(95)": 7726.107,
          "p(99)": 60000.66645
        },
        "thresholds": {
          "p(95)<30000": {
            "ok": true
          },
          "p(99)<45000": {
            "ok": false
          }
        },
        "type": "trend",
        "contains": "time"
      },
      "http_req_tls_handshaking": {
        "type": "trend",
        "contains": "time",
        "values": {
          "avg": 0,
          "min": 0,
          "med": 0,
          "max": 0,
          "p(90)": 0,
          "p(95)": 0,
          "p(99)": 0
        }
      },
      "data_sent": {
        "type": "counter",
        "contains": "data",
        "values": {
          "count": 17491247,
          "rate": 13859.316924403327
        }
      },
      "error_count": {
        "contains": "default",
        "values": {
          "count": 242,
          "rate": 0.19175046214289954
        },
        "type": "counter"
      },
      "http_req_connecting": {
        "type": "trend",
        "contains": "time",
        "values": {
          "min": 0,
          "med": 0,
          "max": 204.5606,
          "p(90)": 0,
          "p(95)": 0,
          "p(99)": 2.404049999999988,
          "avg": 0.10735027337980377
        }
      },
      "order_list_latency": {
        "type": "trend",
        "contains": "default",
        "values": {
          "max": 60394,
          "p(90)": 7611,
          "p(95)": 46999,
          "p(99)": 60012,
          "avg": 5686.748325167483,
          "min": 12,
          "med": 1519
        },
        "thresholds": {
          "p(95)<15000": {
            "ok": false
          }
        }
      },
      "iteration_duration": {
        "type": "trend",
        "contains": "time",
        "values": {
          "p(95)": 51574.97778999991,
          "p(99)": 64005.199268000004,
          "avg": 9515.724407217265,
          "min": 1043.7967,
          "med": 5541.8865,
          "max": 68043.0841,
          "p(90)": 14021.7435
        }
      },
      "http_req_duration{expected_response:true}": {
        "values": {
          "min": 3.223,
          "med": 1112.5122999999999,
          "max": 58711.5174,
          "p(90)": 5217.2729500000005,
          "p(95)": 6423.323574999999,
          "p(99)": 14690.374999999947,
          "avg": 2194.173201725908
        },
        "type": "trend",
        "contains": "time"
      },
      "http_req_waiting": {
        "values": {
          "p(90)": 5946.0845,
          "p(95)": 7721.81805,
          "p(99)": 60000.64594,
          "avg": 3605.200800883636,
          "min": 3.223,
          "med": 1191.3604,
          "max": 60146.1234
        },
        "type": "trend",
        "contains": "time"
      },
      "vus_max": {
        "type": "gauge",
        "contains": "default",
        "values": {
          "value": 300,
          "min": 300,
          "max": 300
        }
      },
      "success_rate": {
        "thresholds": {
          "rate>0.65": {
            "ok": true
          }
        },
        "type": "rate",
        "contains": "default",
        "values": {
          "rate": 0.9366795755167732,
          "passes": 18624,
          "fails": 1259
        }
      },
      "checks": {
        "type": "rate",
        "contains": "default",
        "values": {
          "passes": 31379,
          "fails": 1277,
          "rate": 0.9608953944145027
        },
        "thresholds": {
          "rate>0.65": {
            "ok": true
          }
        }
      },
      "http_req_failed": {
        "thresholds": {
          "rate<0.35": {
            "ok": true
          }
        },
        "type": "rate",
        "contains": "default",
        "values": {
          "fails": 36966,
          "rate": 0.04210826358477365,
          "passes": 1625
        }
      }
    },
    "setup_data": {
      "authToken": "eyJhbGciOiJIUzI1NiIsInR5cCI6IkpXVCJ9.eyJlbWFpbCI6ImFkbWluMkBkZW1vLmNvbSIsInN1YiI6ImIzMDg3ODFjLTMzNzUtNDEyNi04NjJmLTJkZTE1ZTUxYzBkOSIsIm5hbWUiOiJMaW5oIiwicm9sZSI6ImFkbWluIiwiaWF0IjoxNzY1NTcwNTczLCJleHAiOjE3NjU2NTY5NzN9.bHLpO8Kr5c-RySC8nmei0XSCkEqgarfncb7DhttH9gs",
      "customerId": "8b81ead9-3cff-43b7-af0a-4cd4a41aa998",
      "productIds": [
        "4345123f-f0ab-4e6b-b1ee-641b347b6d33",
        "7186a6ce-253f-491e-b05e-539682608d93",
        "fc73fc08-eb0c-47f6-9594-e5e766f088ed",
        "402c2bf8-d6b7-45bd-b7b8-7cb3c443e21c",
        "cadf6dab-702e-4b2e-822e-8e8ffdba0bf8",
        "db804ed4-0574-4956-918a-678d577060e3",
        "51b5a337-f648-4682-8f3d-038f5580544d",
        "e8efae58-8552-4596-a50b-641d5be7023b",
        "c74a7a27-91e0-4990-b8fe-255092e3188f",
        "7c507ef6-33d7-49fc-89fb-c5eb7d2af52c",
        "8badb0d4-8bef-4d52-b340-3009b160bd74",
        "226ec604-5de9-4a98-aa6c-f33fb743112b",
        "0a54bed9-59a0-4aa2-9af4-d8462cd80f98",
        "9085042a-7ee2-4b78-8e3c-7397692ca3ae",
        "67d3667a-d739-4bb5-a37f-1862b006dc3d",
        "a10b18a8-6b32-48a8-a93a-fe244400f02b",
        "713131eb-afd9-4954-aaf6-1dcc06a82827",
        "6b321989-9fbf-4d53-bea9-83044120876c",
        "94857f2a-0f70-46a6-b995-09dade58df77",
        "ae908539-bb1e-4e8c-8012-5782b8661142",
        "6b8ccc2f-fc16-49dc-98ef-fe15439c724a",
        "8ae2170b-b7d3-44b3-b68d-1005b3c822f9",
        "cf81993e-aba6-4d04-9fd0-65e33c893714",
        "c8d02dd6-3c4c-4bbc-a154-9208dea3cfb3",
        "16bbdfb4-752c-4279-a2fc-a0e8a1b8400d",
        "11ed8495-e74e-4cfd-a47d-d79726c7959e",
        "95d91ad3-04d4-4251-b904-b29f9e60c0c0",
        "48ec5500-c53b-4083-89ce-68b494928529",
        "ae0a0bd9-e005-4d50-bc94-8b6c58884a8b",
        "691d6136-b507-4985-964a-ab8d4c26dca6",
        "9d8a7e87-5457-4b49-8cd8-a69622f87c45",
        "20a6203d-f57e-4c58-8bd4-0761c9aef168",
        "a0947964-95b4-4112-ad9b-25d3ec9cffa4",
        "e599e41b-e1c7-47db-8a46-e313e787e5f9",
        "6147219d-9196-4e0d-82e1-c9b8c2b7adb3",
        "a7a860b3-5519-4b8e-b4f2-3471a5524bb4",
        "b5374673-0332-4de9-8e6e-c863a427072f",
        "44f323e4-79a8-4db4-bf45-945fca7469f0",
        "375c099d-b42c-4a44-916d-bd4ea6329684",
        "95f94b82-af7e-4cc0-aa86-c2952f22b001",
        "eb3789cb-b7a9-491e-8dc1-71c9e5ff9f0c",
        "ee5391cc-2e33-4324-9437-51727ab59ebf"
      ],
      "startTime": 1765570574986
    },
    "root_group": {
      "name": "",
      "path": "",
      "id": "d41d8cd98f00b204e9800998ecf8427e",
      "groups": [],
      "checks": [
          {
            "name": "get 200",
            "path": "::get 200",
            "id": "2c445af86d719d43e970db9ef11acf1c",
            "passes": 17704,
            "fails": 30
          },
          {
            "name": "list 200",
            "path": "::list 200",
            "id": "bb957fc3b3b94304050fa1ff782f2f89",
            "passes": 9363,
            "fails": 638
          },
          {
            "name": "create 201",
            "path": "::create 201",
            "id": "156654209db568811cc0f7da2d599478",
            "passes": 3758,
            "fails": 242
          },
          {
            "passes": 554,
            "fails": 367,
            "name": "add item ok",
            "path": "::add item ok",
            "id": "72ca7f09d44ac150d971d4f489557fab"
          }
        ]
    }
  }
}